odoo10_addon_l10n_be_apb_tax-10.0.1.0.0.99.dev4-py2.7-nspkg.pth
odoo/addons/l10n_be_apb_tax/README.rst
odoo/addons/l10n_be_apb_tax/__init__.py
odoo/addons/l10n_be_apb_tax/__manifest__.py
odoo/addons/l10n_be_apb_tax/data/account_account_template_data.xml
odoo/addons/l10n_be_apb_tax/data/account_fiscal_position_tax_template.xml
odoo/addons/l10n_be_apb_tax/data/account_tax_code_template.xml
odoo/addons/l10n_be_apb_tax/data/account_tax_template_apb_data.xml
odoo/addons/l10n_be_apb_tax/i18n/l10n_be_apb_tax.pot
odoo/addons/l10n_be_apb_tax/static/description/icon.png
odoo10_addon_l10n_be_apb_tax-10.0.1.0.0.99.dev4.dist-info/METADATA
odoo10_addon_l10n_be_apb_tax-10.0.1.0.0.99.dev4.dist-info/RECORD
odoo10_addon_l10n_be_apb_tax-10.0.1.0.0.99.dev4.dist-info/WHEEL
odoo10_addon_l10n_be_apb_tax-10.0.1.0.0.99.dev4.dist-info/namespace_packages.txt
odoo10_addon_l10n_be_apb_tax-10.0.1.0.0.99.dev4.dist-info/top_level.txt
